[
  {
    "id": 1,
    "name": "A great story never told",
    "date": "2015-01-01 00:00:00.000",
    "author": "Melissa Sing",
    "comments": "23",
    "tags": [
      "story",
      "cold"
      ],
    "description": "It was a cold December morning, as I sat out on my porch I decided today was the day.",
    "link": "http://bbc.com"
  },
  {
    "id": 2,
    "name": "Builing, Hacking, Creating",
    "date": "2015-02-01 00:00:00.000",
    "author": "Melissa Sing",
    "comments": "11",
    "tags": [
      "building",
      "hack"
      ],
    "description": "Is it better to start from scratch or build on someone elses work. My thoughts.",
    "link": "http://bbc.com"
  },
  {
    "id": 3,
    "name": "Ten reasons why you should travel, or why the city is killing your inner creative",
    "date": "2015-03-01 00:00:00.000",
    "author": "Melissa Sing",
    "comments": "2",
    "tags": [
      "travel",
      "city"
      ],
    "description": "About time for your next adventure.",
    "link": "http://bbc.com"
  },
  {
    "id": 4,
    "name": "We don't have a brig",
    "date": "2015-04-01 00:00:00.000",
    "author": "Melissa Sing",
    "comments": "30",
    "tags": [
      "products",
      "features"
      ],
    "description": "Use this resource to highlight the points of interest of your products. Just a click to open a brief description of each point, allowing your user to get a deep and fast understanding of your product features.",
    "link": "http://bbc.com"
  },
  {
    "id": 5,
    "name": "Every other day it's food, food, food.",
    "date": "2015-04-03 00:00:00.000",
    "author": "Melissa Sing",
    "comments": "18",
    "tags": [
      "food",
      "drink"
      ],
    "description": "I suppose I could part with 'one' and still be feared… I don't 'need' to drink. I can quit anytime I want! Oh, I think we should just stay friends. Noooooo! Five hours? Aw, man! Couldn't you just get me the death penalty?",
    "link": "http://bbc.com"
  },
  {
    "id": 6,
    "name": "Bootstrap Components",
    "date": "2015-04-07 00:00:00.000",
    "author": "Melissa Sing",
    "comments": "43",
    "tags": [
      "bootstrap",
      "components"
      ],
    "description": "How do some of the default bootstrap components looks",
    "link": "http://bbc.com"
  },
  {
    "id": 7,
    "name": "Ah, now the ball's in Farnsworth's court!",
    "date": "2015-04-09 00:00:00.000",
    "author": "Melissa Sing",
    "comments": "9",
    "tags": [
      "fuel",
      "stemcell"
      ],
    "description": "Bender, hurry! This fuel's expensive! Also, we're dying! Fry, we have a crate to deliver. In your time, yes, but nowadays shut up! Besides, these are adult stemcells, harvested from perfectly healthy adults whom I killed for their stemcells. This is the worst part. The calm before the battle.",
    "link": "http://bbc.com"
  },
  {
    "id": 8,
    "name": "But I've never been to the moon!",
    "date": "2015-04-14 00:00:00.000",
    "author": "Melissa Sing",
    "comments": "2",
    "tags": [
      "moon",
      "space"
      ],
    "description": "But I've never been to the moon! I found what I need. And it's not friends, it's things. Can I use the gun? Incidentally, you have a dime up your nose. One hundred dollars.",
    "link": "http://bbc.com"
  }
]